knitout_kniterate_3D/__init__.py
knitout_kniterate_3D/_version.py
knitout_kniterate_3D/knit3D.py
knitout_kniterate_3D/knitout.py
knitout_kniterate_3D-1.0.5.dist-info/LICENSE
knitout_kniterate_3D-1.0.5.dist-info/METADATA
knitout_kniterate_3D-1.0.5.dist-info/WHEEL
knitout_kniterate_3D-1.0.5.dist-info/top_level.txt
knitout_kniterate_3D-1.0.5.dist-info/RECORD
