Metadata-Version: 2.1
Name: knitout-kniterate-3D
Version: 1.0.5
Summary: Code for producing knitout files to do 3D knitting on the kniterate knitting machine (and also optionally adding stitch patterns along the 3D surface).
Home-page: https://github.com/gabrielle-ohlson/knit3D
Author: Gabrielle Ohlson
Author-email: gmoa2017@mymail.pomona.edu
License: UNKNOWN
Platform: UNKNOWN
Classifier: Programming Language :: Python :: 3
Classifier: License :: OSI Approved :: MIT License
Classifier: Operating System :: OS Independent
License-File: LICENSE
Requires-Dist: numpy
Requires-Dist: Pillow
